akadata/__init__.py
akadata/exceptions.py
akadata/status.py
akadata/test.py
akadata-0.3.0.dist-info/DESCRIPTION.rst
akadata-0.3.0.dist-info/METADATA
akadata-0.3.0.dist-info/RECORD
akadata-0.3.0.dist-info/WHEEL
akadata-0.3.0.dist-info/metadata.json
akadata-0.3.0.dist-info/top_level.txt
