Metadata-Version: 2.0
Name: akadata
Version: 0.3.0
Summary: Python port of Akamai EdgeScape client
Home-page: https://github.com/redjack/akadata-py
Author: Andy Freeland
Author-email: andy.freeland@redjack.com
License: MIT
Platform: UNKNOWN
Classifier: License :: OSI Approved :: MIT License
Classifier: Programming Language :: Python :: 2
Classifier: Programming Language :: Python :: 3
Classifier: Programming Language :: Python :: Implementation :: CPython
Classifier: Programming Language :: Python :: Implementation :: PyPy
Requires-Dist: ipaddress; python_version=="2.7"
